Workbook

Sheet Empieza aquí
B1: Lalan AI · Piloto
B3: Para qué es
B4: Para planear y seguir el piloto: cuánto cuesta, con qué salones, cuánto recargar en OpenRouter y qué hay que medir. El libro de la empresa ("Lalan AI - Mi empresa") sigue siendo el de las ganancias y las negociaciones con clientes directos.
B6: Cómo se usa
B7: 1. Hoja SALONES: una fila por salón del piloto (plan, mes en que entra y cuántos mensajes esperas). Los que hay son ejemplos.
B8: 2. Hoja PILOTO: cuánto dura, qué descuento les das (100 % = gratis) y tus gastos. Arriba ves el costo total y la recarga de OpenRouter.
B9: 3. Hoja LISTA DE LANZAMIENTO: lo que tiene que estar listo antes de que escriba la primera clienta.
B10: 4. Cada semana, hoja QUÉ MEDIR: escribe lo real. Lo que se aleje del supuesto, lo actualizas en el libro de la empresa.
B12: Colores
B13: Azul con fondo amarillo = lo escribes tú · Negro = se calcula solo · Rojo = pérdida o tarea con fecha encima

Sheet Piloto
A1: Lalan AI · El piloto
A2: Cuánto cuesta el piloto y qué necesitas tener listo. Escribe en las celdas AZULES con fondo amarillo; los salones van en la hoja Salones. Los valores de partida salen del libro de la empresa (26-sep-2026).
A4: Lo importante
A5: Salones en el piloto | B5: =COUNTA(Salones!$A$5:$A$16) -> 4 | D5: Los que tienen nombre en la hoja Salones.
A6: Lo que cuesta el piloto completo | B6: =SUMIFS('Mes a mes'!$C$29:$H$29,'Mes a mes'!$C$5:$H$5,"<="&MesesPiloto) -> 18245.401 | D6: Todo lo que sale durante los meses del piloto, en pesos: tarjeta, visitas y material.
A7: De eso, en la tarjeta (dólares) | B7: =SUMIFS('Mes a mes'!$C$22:$H$22,'Mes a mes'!$C$5:$H$5,"<="&MesesPiloto) -> 167.325 | D7: Servidores, dominio e IA durante el piloto.
A8: Recarga a OpenRouter antes de empezar | B8: =MAX(MinimoRecarga,CEILING(SUMIFS('Mes a mes'!$C$18:$H$18,'Mes a mes'!$C$5:$H$5,"<="&MesesPiloto)*(1+ColchonIA),5)) -> 30 | D8: La IA de todo el piloto más el colchón, redondeada a 5. Activa además el aviso de saldo bajo en OpenRouter.
A9: Lo que te queda de lo cobrado en el piloto | B9: =SUMIFS('Mes a mes'!$C$15:$H$15,'Mes a mes'!$C$5:$H$5,"<="&MesesPiloto) -> 0 | D9: 0 si el piloto es gratis.
A10: Resultado del piloto | B10: =SUMIFS('Mes a mes'!$C$32:$H$32,'Mes a mes'!$C$5:$H$5,"<="&MesesPiloto) -> -18245.401 | D10: Negativo = lo que inviertes en el piloto.
A11: Primer mes que cubre sus gastos | B11: =IFERROR(INDEX('Mes a mes'!$C$4:$H$4,1,MATCH(1,'Mes a mes'!$C$34:$H$34,0)),"Ninguno en estos 6 meses") -> Ninguno en estos 6 meses | D11: Con estos salones pagando precio normal después del piloto.
A13: Reglas del piloto
A14: Cuántos meses dura el piloto | B14: 3 | C14: meses | D14: Durante estos meses rige el precio del piloto. En la hoja Mes a mes se ven también los 3 meses siguientes, ya a precio normal.
A15: Descuento durante el piloto | B15: 1 | C15: % | D15: 100 % = gratis. 50 % = pagan la mitad. Se puede cambiar el precio de un salón concreto en la hoja Salones.
A16: Primer mes del piloto | B16: 46296 | C16: fecha
A17: Precios de los planes (los mismos del libro de la empresa)
A18: Esencial | B18: 495 | C18: RD$ / mes | D18: Con ITBIS incluido.
A19: Salón | B19: 1490 | C19: RD$ / mes
A20: Lounge | B20: 2990 | C20: RD$ / mes
A21: Parte del precio que te queda (sin ITBIS ni comisión del cobro) | B21: 0.8136 | C21: % | D21: Del libro de la empresa: con ITBIS incluido (18 %) y 4 % de comisión, de cada RD$ 100 te quedan RD$ 81.
A22: Lo que cuesta (se paga con tarjeta, en dólares)
A23: Inteligencia artificial por mensaje de clienta | B23: 0.0033 | C23: US$ | D23: Del libro de la empresa (gpt-4.1-mini con caché y mensajes agrupados). En el piloto lo confirmas en la hoja Qué medir.
A24: Tus mensajes de prueba al mes | B24: 300 | C24: mensajes | D24: Tus pruebas gastan igual que una clienta. Al principio son muchas.
A25: Servidores: app, base de datos y n8n (Railway) | B25: 40 | C25: US$ / mes | D25: Estimado: US$ 25 app y base de datos + US$ 15 n8n.
A26: Dominio, correo y respaldos | B26: 10 | C26: US$ / mes | D26: Estimado.
A27: Voz de la dueña (ElevenLabs) | B27: 0 | C27: US$ / mes | D27: 0 en el piloto: todavía no está construida.
A28: Colchón de saldo en OpenRouter | B28: 0.5 | C28: % | D28: Recarga un poco más de lo que calculas: si un salón escribe mucho más de lo previsto, no se queda sin respuestas.
A29: Recarga mínima en OpenRouter | B29: 20 | C29: US$ | D29: Con US$ 10 o más comprados, OpenRouter sube los límites diarios. Menos de 20 no vale la pena.
A30: Lo que cuesta en pesos
A31: Tasa del dólar (venta) | B31: 59.4618 | C31: RD$ por US$ | D31: Banco Central RD, 24-sep-2026. Actualízala.
A32: Colchón cambiario | B32: 0.08 | C32: % | D32: Por si el dólar sube durante el piloto.
A33: Transporte y visitas a los salones | B33: 2000 | C33: RD$ / mes | D33: Instalar, capacitar y acompañar. EJEMPLO.
A34: Material de arranque (una sola vez) | B34: 1500 | C34: RD$ | D34: Tarjetas con el QR de canciones, stickers, impresiones. Se cuenta en el mes 1. EJEMPLO.
A35: Otros gastos del piloto al mes | B35: 0 | C35: RD$ / mes | D35: Lo que no esté arriba.
A36: → Cuántos pesos cuesta cada dólar (con colchón) | B36: =TasaUSD*(1+Colchon) -> 64.218744 | C36: RD$ por US$

Sheet Salones
A1: Salones del piloto
A2: Una fila por salón. Los que hay son EJEMPLOS: cámbialos por los tuyos. El precio del piloto sale solo del descuento; si con un salón acordaste otra cosa, escribe encima.
A4: Salón | B4: Plan | C4: Mes en que entra | D4: Mensajes de clientas al mes | E4: Precio de lista (RD$) | F4: Precio en el piloto (RD$) | G4: IA al mes (US$) | H4: Contacto / nota
A5: Salón ejemplo · uñas | B5: Esencial | C5: 1 | D5: 150 | E5: =IF(B5="Esencial",PrecioEsencial,IF(B5="Salón",PrecioSalon,IF(B5="Lounge",PrecioLounge,0))) -> 495 | F5: =E5*(1-DescuentoPiloto) -> 0 | G5: =D5*CostoIAMensaje -> 0.495 | H5: EJEMPLO: local de uñas, 1 manicurista
A6: Salón ejemplo · barrio | B6: Salón | C6: 1 | D6: 400 | E6: =IF(B6="Esencial",PrecioEsencial,IF(B6="Salón",PrecioSalon,IF(B6="Lounge",PrecioLounge,0))) -> 1490 | F6: =E6*(1-DescuentoPiloto) -> 0 | G6: =D6*CostoIAMensaje -> 1.32 | H6: EJEMPLO
A7: Salón ejemplo · spa | B7: Lounge | C7: 1 | D7: 700 | E7: =IF(B7="Esencial",PrecioEsencial,IF(B7="Salón",PrecioSalon,IF(B7="Lounge",PrecioLounge,0))) -> 2990 | F7: =E7*(1-DescuentoPiloto) -> 0 | G7: =D7*CostoIAMensaje -> 2.31 | H7: EJEMPLO: tiene Lounge y música
A8: Salón ejemplo · amiga | B8: Salón | C8: 2 | D8: 300 | E8: =IF(B8="Esencial",PrecioEsencial,IF(B8="Salón",PrecioSalon,IF(B8="Lounge",PrecioLounge,0))) -> 1490 | F8: =E8*(1-DescuentoPiloto) -> 0 | G8: =D8*CostoIAMensaje -> 0.99 | H8: EJEMPLO: entra el segundo mes
E9: =IF(B9="Esencial",PrecioEsencial,IF(B9="Salón",PrecioSalon,IF(B9="Lounge",PrecioLounge,0))) -> 0 | F9: =E9*(1-DescuentoPiloto) -> 0 | G9: =D9*CostoIAMensaje -> 0
E10: =IF(B10="Esencial",PrecioEsencial,IF(B10="Salón",PrecioSalon,IF(B10="Lounge",PrecioLounge,0))) -> 0 | F10: =E10*(1-DescuentoPiloto) -> 0 | G10: =D10*CostoIAMensaje -> 0
E11: =IF(B11="Esencial",PrecioEsencial,IF(B11="Salón",PrecioSalon,IF(B11="Lounge",PrecioLounge,0))) -> 0 | F11: =E11*(1-DescuentoPiloto) -> 0 | G11: =D11*CostoIAMensaje -> 0
E12: =IF(B12="Esencial",PrecioEsencial,IF(B12="Salón",PrecioSalon,IF(B12="Lounge",PrecioLounge,0))) -> 0 | F12: =E12*(1-DescuentoPiloto) -> 0 | G12: =D12*CostoIAMensaje -> 0
E13: =IF(B13="Esencial",PrecioEsencial,IF(B13="Salón",PrecioSalon,IF(B13="Lounge",PrecioLounge,0))) -> 0 | F13: =E13*(1-DescuentoPiloto) -> 0 | G13: =D13*CostoIAMensaje -> 0
E14: =IF(B14="Esencial",PrecioEsencial,IF(B14="Salón",PrecioSalon,IF(B14="Lounge",PrecioLounge,0))) -> 0 | F14: =E14*(1-DescuentoPiloto) -> 0 | G14: =D14*CostoIAMensaje -> 0
E15: =IF(B15="Esencial",PrecioEsencial,IF(B15="Salón",PrecioSalon,IF(B15="Lounge",PrecioLounge,0))) -> 0 | F15: =E15*(1-DescuentoPiloto) -> 0 | G15: =D15*CostoIAMensaje -> 0
E16: =IF(B16="Esencial",PrecioEsencial,IF(B16="Salón",PrecioSalon,IF(B16="Lounge",PrecioLounge,0))) -> 0 | F16: =E16*(1-DescuentoPiloto) -> 0 | G16: =D16*CostoIAMensaje -> 0
A17: Total | D17: =SUM(D5:D16) -> 1550 | E17: =SUM(E5:E16) -> 6465 | F17: =SUM(F5:F16) -> 0 | G17: =SUM(G5:G16) -> 5.115
A19: Mensajes de clientas al mes, como referencia: un local pequeño 100-200, un salón con equipo 300-500, un spa con Lounge 600-1.000. Lo real lo ves en Métricas → Lo que hizo Lalan.

Sheet Mes a mes
A1: El piloto mes a mes
A2: Durante el piloto y los 3 meses siguientes, ya a precio normal. No se edita: sale de Piloto y Salones.
A4: Concepto | B4: Total | C4: =EDATE(InicioPiloto,0) -> 46296 | D4: =EDATE(InicioPiloto,1) -> 46327 | E4: =EDATE(InicioPiloto,2) -> 46357 | F4: =EDATE(InicioPiloto,3) -> 46388 | G4: =EDATE(InicioPiloto,4) -> 46419 | H4: =EDATE(InicioPiloto,5) -> 46447
A5: Mes n.º | C5: 1 | D5: 2 | E5: 3 | F5: 4 | G5: 5 | H5: 6
A6: ¿Es mes de piloto? | C6: =IF(C5<=MesesPiloto,"Piloto","Normal") -> Piloto | D6: =IF(D5<=MesesPiloto,"Piloto","Normal") -> Piloto | E6: =IF(E5<=MesesPiloto,"Piloto","Normal") -> Piloto | F6: =IF(F5<=MesesPiloto,"Piloto","Normal") -> Normal | G6: =IF(G5<=MesesPiloto,"Piloto","Normal") -> Normal | H6: =IF(H5<=MesesPiloto,"Piloto","Normal") -> Normal
A9: Salones
A10: Salones en el piloto | B10: =H10 -> 4 | C10: =COUNTIFS(Salones!$C$5:$C$16,"<="&C$5,Salones!$A$5:$A$16,"<>") -> 3 | D10: =COUNTIFS(Salones!$C$5:$C$16,"<="&D$5,Salones!$A$5:$A$16,"<>") -> 4 | E10: =COUNTIFS(Salones!$C$5:$C$16,"<="&E$5,Salones!$A$5:$A$16,"<>") -> 4 | F10: =COUNTIFS(Salones!$C$5:$C$16,"<="&F$5,Salones!$A$5:$A$16,"<>") -> 4 | G10: =COUNTIFS(Salones!$C$5:$C$16,"<="&G$5,Salones!$A$5:$A$16,"<>") -> 4 | H10: =COUNTIFS(Salones!$C$5:$C$16,"<="&H$5,Salones!$A$5:$A$16,"<>") -> 4
A11: Mensajes de clientas | B11: =SUM(C11:H11) -> 9000 | C11: =SUMIFS(Salones!$D$5:$D$16,Salones!$C$5:$C$16,"<="&C$5) -> 1250 | D11: =SUMIFS(Salones!$D$5:$D$16,Salones!$C$5:$C$16,"<="&D$5) -> 1550 | E11: =SUMIFS(Salones!$D$5:$D$16,Salones!$C$5:$C$16,"<="&E$5) -> 1550 | F11: =SUMIFS(Salones!$D$5:$D$16,Salones!$C$5:$C$16,"<="&F$5) -> 1550 | G11: =SUMIFS(Salones!$D$5:$D$16,Salones!$C$5:$C$16,"<="&G$5) -> 1550 | H11: =SUMIFS(Salones!$D$5:$D$16,Salones!$C$5:$C$16,"<="&H$5) -> 1550
A13: Lo que entra
A14: Cobrado a los salones | B14: =SUM(C14:H14) -> 19395 | C14: =IF(C$5<=MesesPiloto,SUMIFS(Salones!$F$5:$F$16,Salones!$C$5:$C$16,"<="&C$5),SUMIFS(Salones!$E$5:$E$16,Salones!$C$5:$C$16,"<="&C$5)) -> 0 | D14: =IF(D$5<=MesesPiloto,SUMIFS(Salones!$F$5:$F$16,Salones!$C$5:$C$16,"<="&D$5),SUMIFS(Salones!$E$5:$E$16,Salones!$C$5:$C$16,"<="&D$5)) -> 0 | E14: =IF(E$5<=MesesPiloto,SUMIFS(Salones!$F$5:$F$16,Salones!$C$5:$C$16,"<="&E$5),SUMIFS(Salones!$E$5:$E$16,Salones!$C$5:$C$16,"<="&E$5)) -> 0 | F14: =IF(F$5<=MesesPiloto,SUMIFS(Salones!$F$5:$F$16,Salones!$C$5:$C$16,"<="&F$5),SUMIFS(Salones!$E$5:$E$16,Salones!$C$5:$C$16,"<="&F$5)) -> 6465 | G14: =IF(G$5<=MesesPiloto,SUMIFS(Salones!$F$5:$F$16,Salones!$C$5:$C$16,"<="&G$5),SUMIFS(Salones!$E$5:$E$16,Salones!$C$5:$C$16,"<="&G$5)) -> 6465 | H14: =IF(H$5<=MesesPiloto,SUMIFS(Salones!$F$5:$F$16,Salones!$C$5:$C$16,"<="&H$5),SUMIFS(Salones!$E$5:$E$16,Salones!$C$5:$C$16,"<="&H$5)) -> 6465
A15: Lo que te queda (sin ITBIS ni comisión) | B15: =SUM(C15:H15) -> 15779.772 | C15: =C14*FactorNeto -> 0 | D15: =D14*FactorNeto -> 0 | E15: =E14*FactorNeto -> 0 | F15: =F14*FactorNeto -> 5259.924 | G15: =G14*FactorNeto -> 5259.924 | H15: =H14*FactorNeto -> 5259.924
A17: Lo que sale (en dólares)
A18: Inteligencia artificial (OpenRouter) | B18: =SUM(C18:H18) -> 35.64 | C18: =(C11+MensajesPruebas)*CostoIAMensaje -> 5.115 | D18: =(D11+MensajesPruebas)*CostoIAMensaje -> 6.105 | E18: =(E11+MensajesPruebas)*CostoIAMensaje -> 6.105 | F18: =(F11+MensajesPruebas)*CostoIAMensaje -> 6.105 | G18: =(G11+MensajesPruebas)*CostoIAMensaje -> 6.105 | H18: =(H11+MensajesPruebas)*CostoIAMensaje -> 6.105
A19: Servidores | B19: =SUM(C19:H19) -> 240 | C19: =Servidores -> 40 | D19: =Servidores -> 40 | E19: =Servidores -> 40 | F19: =Servidores -> 40 | G19: =Servidores -> 40 | H19: =Servidores -> 40
A20: Dominio, correo y respaldos | B20: =SUM(C20:H20) -> 60 | C20: =Dominio -> 10 | D20: =Dominio -> 10 | E20: =Dominio -> 10 | F20: =Dominio -> 10 | G20: =Dominio -> 10 | H20: =Dominio -> 10
A21: Voz (ElevenLabs) | B21: =SUM(C21:H21) -> 0 | C21: =VozElevenLabs -> 0 | D21: =VozElevenLabs -> 0 | E21: =VozElevenLabs -> 0 | F21: =VozElevenLabs -> 0 | G21: =VozElevenLabs -> 0 | H21: =VozElevenLabs -> 0
A22: Total en dólares | B22: =SUM(C22:H22) -> 335.64 | C22: =SUM(C18:C21) -> 55.115 | D22: =SUM(D18:D21) -> 56.105 | E22: =SUM(E18:E21) -> 56.105 | F22: =SUM(F18:F21) -> 56.105 | G22: =SUM(G18:G21) -> 56.105 | H22: =SUM(H18:H21) -> 56.105
A24: Lo que sale (en pesos)
A25: Los dólares, pasados a pesos | B25: =SUM(C25:H25) -> 21554.379 | C25: =C22*FactorCambio -> 3539.4161 | D25: =D22*FactorCambio -> 3602.9926 | E25: =E22*FactorCambio -> 3602.9926 | F25: =F22*FactorCambio -> 3602.9926 | G25: =G22*FactorCambio -> 3602.9926 | H25: =H22*FactorCambio -> 3602.9926
A26: Transporte y visitas | B26: =SUM(C26:H26) -> 12000 | C26: =Visitas -> 2000 | D26: =Visitas -> 2000 | E26: =Visitas -> 2000 | F26: =Visitas -> 2000 | G26: =Visitas -> 2000 | H26: =Visitas -> 2000
A27: Material de arranque | B27: =SUM(C27:H27) -> 1500 | C27: =IF(C$5=1,Material,0) -> 1500 | D27: =IF(D$5=1,Material,0) -> 0 | E27: =IF(E$5=1,Material,0) -> 0 | F27: =IF(F$5=1,Material,0) -> 0 | G27: =IF(G$5=1,Material,0) -> 0 | H27: =IF(H$5=1,Material,0) -> 0
A28: Otros | B28: =SUM(C28:H28) -> 0 | C28: =Otros -> 0 | D28: =Otros -> 0 | E28: =Otros -> 0 | F28: =Otros -> 0 | G28: =Otros -> 0 | H28: =Otros -> 0
A29: TODO LO QUE SALE | B29: =SUM(C29:H29) -> 35054.379 | C29: =SUM(C25:C28) -> 7039.4161 | D29: =SUM(D25:D28) -> 5602.9926 | E29: =SUM(E25:E28) -> 5602.9926 | F29: =SUM(F25:F28) -> 5602.9926 | G29: =SUM(G25:G28) -> 5602.9926 | H29: =SUM(H25:H28) -> 5602.9926
A31: Resultado
A32: Resultado del mes | B32: =SUM(C32:H32) -> -19274.607 | C32: =C15-C29 -> -7039.4161 | D32: =D15-D29 -> -5602.9926 | E32: =E15-E29 -> -5602.9926 | F32: =F15-F29 -> -343.06863 | G32: =G15-G29 -> -343.06863 | H32: =H15-H29 -> -343.06863
A33: Acumulado | B33: =H33 -> -19274.607 | C33: =C32 -> -7039.4161 | D33: =C33+D32 -> -12642.409 | E33: =D33+E32 -> -18245.401 | F33: =E33+F32 -> -18588.47 | G33: =F33+G32 -> -18931.539 | H33: =G33+H32 -> -19274.607
A34: ¿Cubre sus gastos? (1 = sí) | C34: =IF(C32>=0,1,0) -> 0 | D34: =IF(D32>=0,1,0) -> 0 | E34: =IF(E32>=0,1,0) -> 0 | F34: =IF(F32>=0,1,0) -> 0 | G34: =IF(G32>=0,1,0) -> 0 | H34: =IF(H32>=0,1,0) -> 0

Sheet Qué medir
A1: Qué medir en el piloto
A2: El piloto sirve para cambiar supuestos por datos. Escribe el valor real cuando lo tengas: si se aleja más de lo tolerado, actualiza ese número en el libro de la empresa (Supuestos o Planes).
A3: Tolerancia antes de actualizar | B3: 0.2
A5: Qué | B5: Supuesto (libro de la empresa) | C5: Real en el piloto | D5: Dónde se ve | E5: Diferencia | F5: ¿Qué hacer?
A6: Mensajes de clientas al mes (salón típico) | B6: 400 | D6: Métricas → Lo que hizo Lalan (Chats atendidos, respuestas), 'Este mes'. | E6: =IF(C6="","",IF(B6=0,C6-B6,(C6-B6)/B6)) | F6: =IF(C6="","Pendiente",IF(B6=0,IF(C6=0,"Se parece","Revísalo"),IF(ABS((C6-B6)/B6)<=Tolerancia,"Se parece","Actualiza el libro de la empresa"))) -> Pendiente
A7: Costo de IA por mensaje de clienta | B7: 0.0033 | D7: OpenRouter → Activity: gasto del mes ÷ mensajes de clientas del mes. | E7: =IF(C7="","",IF(B7=0,C7-B7,(C7-B7)/B7)) | F7: =IF(C7="","Pendiente",IF(B7=0,IF(C7=0,"Se parece","Revísalo"),IF(ABS((C7-B7)/B7)<=Tolerancia,"Se parece","Actualiza el libro de la empresa"))) -> Pendiente
A8: Tokens de entrada por llamada | B8: 6500 | D8: OpenRouter → Activity → una llamada cualquiera (Tokens / prompt). | E8: =IF(C8="","",IF(B8=0,C8-B8,(C8-B8)/B8)) | F8: =IF(C8="","Pendiente",IF(B8=0,IF(C8=0,"Se parece","Revísalo"),IF(ABS((C8-B8)/B8)<=Tolerancia,"Se parece","Actualiza el libro de la empresa"))) -> Pendiente
A9: Parte de la entrada en caché | B9: 0.55 | D9: OpenRouter → Activity: cached tokens ÷ tokens de entrada. | E9: =IF(C9="","",IF(B9=0,C9-B9,(C9-B9)/B9)) | F9: =IF(C9="","Pendiente",IF(B9=0,IF(C9=0,"Se parece","Revísalo"),IF(ABS((C9-B9)/B9)<=Tolerancia,"Se parece","Actualiza el libro de la empresa"))) -> Pendiente
A10: Mensajes que llegan en ráfaga (se contestan juntos) | B10: 0.2 | D10: 1 − (respuestas de Lalan ÷ mensajes de clientas). | E10: =IF(C10="","",IF(B10=0,C10-B10,(C10-B10)/B10)) | F10: =IF(C10="","Pendiente",IF(B10=0,IF(C10=0,"Se parece","Revísalo"),IF(ABS((C10-B10)/B10)<=Tolerancia,"Se parece","Actualiza el libro de la empresa"))) -> Pendiente
A11: Mensajes que llegan como nota de voz | B11: 0.3 | D11: Chats: cuántos dicen '(Nota de voz)'. | E11: =IF(C11="","",IF(B11=0,C11-B11,(C11-B11)/B11)) | F11: =IF(C11="","Pendiente",IF(B11=0,IF(C11=0,"Se parece","Revísalo"),IF(ABS((C11-B11)/B11)<=Tolerancia,"Se parece","Actualiza el libro de la empresa"))) -> Pendiente
A12: Parte de las citas que agenda Lalan | B12: 0.5 | D12: Métricas → 'Agendó el X % de las que se agendaron'. | E12: =IF(C12="","",IF(B12=0,C12-B12,(C12-B12)/B12)) | F12: =IF(C12="","Pendiente",IF(B12=0,IF(C12=0,"Se parece","Revísalo"),IF(ABS((C12-B12)/B12)<=Tolerancia,"Se parece","Actualiza el libro de la empresa"))) -> Pendiente
A13: Horas de soporte por salón al mes | B13: 0.5 | D13: Anótalo tú: llamadas, visitas, dudas por WhatsApp. | E13: =IF(C13="","",IF(B13=0,C13-B13,(C13-B13)/B13)) | F13: =IF(C13="","Pendiente",IF(B13=0,IF(C13=0,"Se parece","Revísalo"),IF(ABS((C13-B13)/B13)<=Tolerancia,"Se parece","Actualiza el libro de la empresa"))) -> Pendiente
A14: Búsquedas de música por salón al día (Lounge) | B14: 15 | D14: Google Cloud → YouTube Data API → Cuotas (unidades ÷ 100 ÷ salones). | E14: =IF(C14="","",IF(B14=0,C14-B14,(C14-B14)/B14)) | F14: =IF(C14="","Pendiente",IF(B14=0,IF(C14=0,"Se parece","Revísalo"),IF(ABS((C14-B14)/B14)<=Tolerancia,"Se parece","Actualiza el libro de la empresa"))) -> Pendiente
A15: Salones que se van durante el piloto | B15: 0 | D15: Los que dejan de usarlo. Si alguno se va, pregúntale por qué. | E15: =IF(C15="","",IF(B15=0,C15-B15,(C15-B15)/B15)) | F15: =IF(C15="","Pendiente",IF(B15=0,IF(C15=0,"Se parece","Revísalo"),IF(ABS((C15-B15)/B15)<=Tolerancia,"Se parece","Actualiza el libro de la empresa"))) -> Pendiente

Sheet Lista de lanzamiento
A1: Antes de que la primera clienta escriba
A2: Marca 'Sí' cuando esté hecho. Lo que va en rojo tiene fecha que no espera.
A4: Tarea | B4: ¿Hecho? | C4: Quién | D4: Fecha límite | E4: Nota
A5: Meta: poner método de pago en la cuenta de WhatsApp Business | B5: No | D5: 46295 | E5: Desde el 1-oct Meta cobra las respuestas pasadas las 1.000 gratis. Cada salón, su propia tarjeta.
A6: Meta: plantillas de aviso a la dueña aprobadas | B6: No | E6: lalan_chat_atencion y lalan_cita_sin_especialista.
A7: OpenRouter: recargar (ver hoja Piloto) y activar aviso de saldo bajo | B7: No | E7: Sin saldo, Lalan no responde (la app avisa a la dueña).
A8: Backend: correr el SQL de categorías, db push y reiniciar | B8: No | E8: prisma/sql/2026-09-26-categorias-propias.sql, luego npx prisma db push.
A9: n8n: reimportar los dos flujos y elegir la credencial Lalan · Secreto | B9: No | E9: Entrada WhatsApp (con el nodo '¿Sigue vigente?') y Salidas.
A10: Servidor fijo en lugar del túnel de desarrollo | B10: No | E10: La URL de la API en 'Configuración Lalan' tiene que ser la del servidor, no devtunnels.
A11: Respaldo automático de la base de datos | B11: No | E11: Diario. Probar una vez que se puede restaurar.
A12: Por cada salón: conectar su número de WhatsApp | B12: No | E12: Panel de bots → WhatsApp → phone number ID.
A13: Por cada salón: moneda base, tasa del dólar y catálogo en la moneda correcta | B13: No | E13: Ajustes → Monedas.
A14: Por cada salón: zonas con sus categorías y especialistas | B14: No | E14: Sin esto Lalan no sabe a quién darle cada cita.
A15: Por cada salón: número y nombre para los avisos a la dueña | B15: No | E15: Ajustes → avisos por WhatsApp.
A16: Por cada salón: 15 minutos de capacitación con la dueña | B16: No | E16: Cómo retomar un chat, cómo contestar un aviso, dónde ver Métricas.
A17: Acordar por escrito las reglas del piloto | B17: No | E17: Cuánto dura, qué cuesta después, qué pasa con sus datos si se va.
... A20: Revisión al final de cada semana: hoja Qué medir | B20: No | E20: Lo que se aleje, al libro de la empresa.
A22: Hechas | B22: =COUNTIF(B5:B20,"Sí")&" de "&COUNTA(A5:A20) -> 0 de 16
